dfquery/__init__.py
dfquery/dfquery.py
dfquery-0.0.2.dist-info/METADATA
dfquery-0.0.2.dist-info/WHEEL
dfquery-0.0.2.dist-info/top_level.txt
dfquery-0.0.2.dist-info/RECORD
